tempclone/__init__.py
tempclone/cli.py
tests/__init__.py
tests/test_cli.py
tempclone-1.0.4.dist-info/LICENSE
tempclone-1.0.4.dist-info/METADATA
tempclone-1.0.4.dist-info/WHEEL
tempclone-1.0.4.dist-info/entry_points.txt
tempclone-1.0.4.dist-info/top_level.txt
tempclone-1.0.4.dist-info/RECORD
