Metadata-Version: 2.1
Name: tempclone
Version: 1.0.4
Summary: CLI to automate the creation of new projects from GitHub templates
Home-page: https://github.com/yourusername/tempclone
Author: Matheus
Author-email: matheusmlfg@gmail.com
License: UNKNOWN
Platform: UNKNOWN
Classifier: Programming Language :: Python :: 3
Classifier: License :: OSI Approved :: MIT License
Classifier: Operating System :: OS Independent
Requires-Python: >=3.6
License-File: LICENSE
Requires-Dist: click
Requires-Dist: requests
